f_yeah-0.6.0.dist-info/licenses/LICENSE.txt
fyeah/__init__.py
fyeah/_escaping.py
fyeah/_fyeah.py
fyeah/_tyeah.py
f_yeah-0.6.0.dist-info/METADATA
f_yeah-0.6.0.dist-info/WHEEL
f_yeah-0.6.0.dist-info/top_level.txt
f_yeah-0.6.0.dist-info/RECORD
