Metadata-Version: 2.4
Name: f-yeah
Version: 0.6.0
Summary: Reusable f-strings and t-strings
Author-email: Jeremiah Paige <ucodery@gmail.com>
License: Copyright (c) 2019, Jeremiah Paige
Project-URL: Home, https://github.com/ucodery/fyeah
Classifier: License :: OSI Approved :: BSD License
Requires-Python: >=3.14
License-File: LICENSE.txt
Dynamic: license-file
